aiogram_uptodate/__init__.py
aiogram_uptodate/common.py
aiogram_uptodate/dialog_calendar.py
aiogram_uptodate/dialog_timesheet.py
aiogram_uptodate/schemas.py
aiogram_uptodate/simple_calendar.py
aiogram_uptodate/tests/__init__.py
aiogram_uptodate/tests/test_dialog_uptodate.py
aiogram_uptodate/tests/test_simple_uptodate.py
aiogram_uptodate-0.5.2.dist-info/LICENSE.txt
aiogram_uptodate-0.5.2.dist-info/METADATA
aiogram_uptodate-0.5.2.dist-info/WHEEL
aiogram_uptodate-0.5.2.dist-info/RECORD
