Metadata-Version: 2.1
Name: aiogram_uptodate
Version: 0.5.2
Summary: Simple Datepicker for Aiogram Telegram bots
Home-page: https://github.com/antonyartsev/aiogram_uptodate
License: MIT
Author: Andrii Nikolabai
Author-email: nikolabay.as@gmail.com
Requires-Python: >=3.8,<4.0
Classifier: Development Status :: 3 - Alpha
Classifier: Intended Audience :: Developers
Classifier: License :: OSI Approved :: MIT License
Classifier: Programming Language :: Python :: 3
Classifier: Programming Language :: Python :: 3.8
Classifier: Programming Language :: Python :: 3.9
Classifier: Programming Language :: Python :: 3.10
Classifier: Programming Language :: Python :: 3.11
Classifier: Programming Language :: Python :: 3.12
Classifier: Topic :: Software Development :: Libraries :: Python Modules
Requires-Dist: aiogram (>=3.0,<4.0)
